inmanta_plugins/rest/__init__.py
inmanta_plugins/rest/setup.cfg
inmanta_plugins/rest/model/_init.cf
inmanta_module_rest-1.0.1.dist-info/METADATA
inmanta_module_rest-1.0.1.dist-info/WHEEL
inmanta_module_rest-1.0.1.dist-info/top_level.txt
inmanta_module_rest-1.0.1.dist-info/RECORD
