Metadata-Version: 2.1
Name: inmanta-module-rest
Version: 1.0.1
License: Apache 2.0
Requires-Dist: inmanta-module-std
Requires-Dist: requests<3,>=2.25
Requires-Dist: jq<2,>=1.4
